venmo_client/__init__.py
venmo_client/auth.py
venmo_client/cli.py
venmo_client/client.py
venmo_client/console.py
venmo_client/model/__init__.py
venmo_client/model/transaction.py
venmo_client/model/user.py
venmo_client/util.py
venmo_client-0.7.1.dist-info/entry_points.txt
venmo_client-0.7.1.dist-info/LICENSE
venmo_client-0.7.1.dist-info/WHEEL
venmo_client-0.7.1.dist-info/METADATA
venmo_client-0.7.1.dist-info/RECORD
