Metadata-Version: 2.1
Name: venmo-client
Version: 0.7.1
Summary: 
License: MIT
Author: Sharad Vikram
Author-email: sharad.vikram@gmail.com
Requires-Python: >=3.8,<4.0
Classifier: License :: OSI Approved :: MIT License
Classifier: Programming Language :: Python :: 3
Classifier: Programming Language :: Python :: 3.10
Classifier: Programming Language :: Python :: 3.8
Classifier: Programming Language :: Python :: 3.9
Requires-Dist: click (>=8.0.1,<9.0.0)
Requires-Dist: requests
Requires-Dist: rich (>=10.7.0,<11.0.0)
